{"spec":{"title":"CSS Fonts Module Level 5","url":"https://drafts.csswg.org/css-fonts-5/"},"idlparsed":{"jsNames":{"constructors":{},"functions":{"Window":["CSSFontFaceDescriptors","CSSFontFaceRule"]}},"idlNames":{"CSSFontFaceDescriptors":{"type":"interface","name":"CSSFontFaceDescriptors","inheritance":"CSSStyleDeclaration","members":[{"type":"attribute","name":"src","idlType":{"type":"attribute-type","extAttrs":[{"type":"extended-attribute","name":"LegacyNullToEmptyString","rhs":null,"arguments":[]}],"generic":"","nullable":false,"union":false,"idlType":"CSSOMString"},"extAttrs":[],"special":"","readonly":false},{"type":"attribute","name":"fontFamily","idlType":{"type":"attribute-type","extAttrs":[{"type":"extended-attribute","name":"LegacyNullToEmptyString","rhs":null,"arguments":[]}],"generic":"","nullable":false,"union":false,"idlType":"CSSOMString"},"extAttrs":[],"special":"","readonly":false},{"type":"attribute","name":"font-family","idlType":{"type":"attribute-type","extAttrs":[{"type":"extended-attribute","name":"LegacyNullToEmptyString","rhs":null,"arguments":[]}],"generic":"","nullable":false,"union":false,"idlType":"CSSOMString"},"extAttrs":[],"special":"","readonly":false},{"type":"attribute","name":"fontStyle","idlType":{"type":"attribute-type","extAttrs":[{"type":"extended-attribute","name":"LegacyNullToEmptyString","rhs":null,"arguments":[]}],"generic":"","nullable":false,"union":false,"idlType":"CSSOMString"},"extAttrs":[],"special":"","readonly":false},{"type":"attribute","name":"font-style","idlType":{"type":"attribute-type","extAttrs":[{"type":"extended-attribute","name":"LegacyNullToEmptyString","rhs":null,"arguments":[]}],"generic":"","nullable":false,"union":false,"idlType":"CSSOMString"},"extAttrs":[],"special":"","readonly":false},{"type":"attribute","name":"fontWeight","idlType":{"type":"attribute-type","extAttrs":[{"type":"extended-attribute","name":"LegacyNullToEmptyString","rhs":null,"arguments":[]}],"generic":"","nullable":false,"union":false,"idlType":"CSSOMString"},"extAttrs":[],"special":"","readonly":false},{"type":"attribute","name":"font-weight","idlType":{"type":"attribute-type","extAttrs":[{"type":"extended-attribute","name":"LegacyNullToEmptyString","rhs":null,"arguments":[]}],"generic":"","nullable":false,"union":false,"idlType":"CSSOMString"},"extAttrs":[],"special":"","readonly":false},{"type":"attribute","name":"fontStretch","idlType":{"type":"attribute-type","extAttrs":[{"type":"extended-attribute","name":"LegacyNullToEmptyString","rhs":null,"arguments":[]}],"generic":"","nullable":false,"union":false,"idlType":"CSSOMString"},"extAttrs":[],"special":"","readonly":false},{"type":"attribute","name":"font-stretch","idlType":{"type":"attribute-type","extAttrs":[{"type":"extended-attribute","name":"LegacyNullToEmptyString","rhs":null,"arguments":[]}],"generic":"","nullable":false,"union":false,"idlType":"CSSOMString"},"extAttrs":[],"special":"","readonly":false},{"type":"attribute","name":"fontWidth","idlType":{"type":"attribute-type","extAttrs":[{"type":"extended-attribute","name":"LegacyNullToEmptyString","rhs":null,"arguments":[]}],"generic":"","nullable":false,"union":false,"idlType":"CSSOMString"},"extAttrs":[],"special":"","readonly":false},{"type":"attribute","name":"font-width","idlType":{"type":"attribute-type","extAttrs":[{"type":"extended-attribute","name":"LegacyNullToEmptyString","rhs":null,"arguments":[]}],"generic":"","nullable":false,"union":false,"idlType":"CSSOMString"},"extAttrs":[],"special":"","readonly":false},{"type":"attribute","name":"fontSize","idlType":{"type":"attribute-type","extAttrs":[{"type":"extended-attribute","name":"LegacyNullToEmptyString","rhs":null,"arguments":[]}],"generic":"","nullable":false,"union":false,"idlType":"CSSOMString"},"extAttrs":[],"special":"","readonly":false},{"type":"attribute","name":"font-size","idlType":{"type":"attribute-type","extAttrs":[{"type":"extended-attribute","name":"LegacyNullToEmptyString","rhs":null,"arguments":[]}],"generic":"","nullable":false,"union":false,"idlType":"CSSOMString"},"extAttrs":[],"special":"","readonly":false},{"type":"attribute","name":"sizeAdjust","idlType":{"type":"attribute-type","extAttrs":[{"type":"extended-attribute","name":"LegacyNullToEmptyString","rhs":null,"arguments":[]}],"generic":"","nullable":false,"union":false,"idlType":"CSSOMString"},"extAttrs":[],"special":"","readonly":false},{"type":"attribute","name":"size-adjust","idlType":{"type":"attribute-type","extAttrs":[{"type":"extended-attribute","name":"LegacyNullToEmptyString","rhs":null,"arguments":[]}],"generic":"","nullable":false,"union":false,"idlType":"CSSOMString"},"extAttrs":[],"special":"","readonly":false},{"type":"attribute","name":"unicodeRange","idlType":{"type":"attribute-type","extAttrs":[{"type":"extended-attribute","name":"LegacyNullToEmptyString","rhs":null,"arguments":[]}],"generic":"","nullable":false,"union":false,"idlType":"CSSOMString"},"extAttrs":[],"special":"","readonly":false},{"type":"attribute","name":"unicode-range","idlType":{"type":"attribute-type","extAttrs":[{"type":"extended-attribute","name":"LegacyNullToEmptyString","rhs":null,"arguments":[]}],"generic":"","nullable":false,"union":false,"idlType":"CSSOMString"},"extAttrs":[],"special":"","readonly":false},{"type":"attribute","name":"fontFeatureSettings","idlType":{"type":"attribute-type","extAttrs":[{"type":"extended-attribute","name":"LegacyNullToEmptyString","rhs":null,"arguments":[]}],"generic":"","nullable":false,"union":false,"idlType":"CSSOMString"},"extAttrs":[],"special":"","readonly":false},{"type":"attribute","name":"font-feature-settings","idlType":{"type":"attribute-type","extAttrs":[{"type":"extended-attribute","name":"LegacyNullToEmptyString","rhs":null,"arguments":[]}],"generic":"","nullable":false,"union":false,"idlType":"CSSOMString"},"extAttrs":[],"special":"","readonly":false},{"type":"attribute","name":"fontVariationSettings","idlType":{"type":"attribute-type","extAttrs":[{"type":"extended-attribute","name":"LegacyNullToEmptyString","rhs":null,"arguments":[]}],"generic":"","nullable":false,"union":false,"idlType":"CSSOMString"},"extAttrs":[],"special":"","readonly":false},{"type":"attribute","name":"font-variation-settings","idlType":{"type":"attribute-type","extAttrs":[{"type":"extended-attribute","name":"LegacyNullToEmptyString","rhs":null,"arguments":[]}],"generic":"","nullable":false,"union":false,"idlType":"CSSOMString"},"extAttrs":[],"special":"","readonly":false},{"type":"attribute","name":"fontNamedInstance","idlType":{"type":"attribute-type","extAttrs":[{"type":"extended-attribute","name":"LegacyNullToEmptyString","rhs":null,"arguments":[]}],"generic":"","nullable":false,"union":false,"idlType":"CSSOMString"},"extAttrs":[],"special":"","readonly":false},{"type":"attribute","name":"font-named-instance","idlType":{"type":"attribute-type","extAttrs":[{"type":"extended-attribute","name":"LegacyNullToEmptyString","rhs":null,"arguments":[]}],"generic":"","nullable":false,"union":false,"idlType":"CSSOMString"},"extAttrs":[],"special":"","readonly":false},{"type":"attribute","name":"fontDisplay","idlType":{"type":"attribute-type","extAttrs":[{"type":"extended-attribute","name":"LegacyNullToEmptyString","rhs":null,"arguments":[]}],"generic":"","nullable":false,"union":false,"idlType":"CSSOMString"},"extAttrs":[],"special":"","readonly":false},{"type":"attribute","name":"font-display","idlType":{"type":"attribute-type","extAttrs":[{"type":"extended-attribute","name":"LegacyNullToEmptyString","rhs":null,"arguments":[]}],"generic":"","nullable":false,"union":false,"idlType":"CSSOMString"},"extAttrs":[],"special":"","readonly":false},{"type":"attribute","name":"fontLanguageOverride","idlType":{"type":"attribute-type","extAttrs":[{"type":"extended-attribute","name":"LegacyNullToEmptyString","rhs":null,"arguments":[]}],"generic":"","nullable":false,"union":false,"idlType":"CSSOMString"},"extAttrs":[],"special":"","readonly":false},{"type":"attribute","name":"font-language-override","idlType":{"type":"attribute-type","extAttrs":[{"type":"extended-attribute","name":"LegacyNullToEmptyString","rhs":null,"arguments":[]}],"generic":"","nullable":false,"union":false,"idlType":"CSSOMString"},"extAttrs":[],"special":"","readonly":false},{"type":"attribute","name":"ascentOverride","idlType":{"type":"attribute-type","extAttrs":[{"type":"extended-attribute","name":"LegacyNullToEmptyString","rhs":null,"arguments":[]}],"generic":"","nullable":false,"union":false,"idlType":"CSSOMString"},"extAttrs":[],"special":"","readonly":false},{"type":"attribute","name":"ascent-override","idlType":{"type":"attribute-type","extAttrs":[{"type":"extended-attribute","name":"LegacyNullToEmptyString","rhs":null,"arguments":[]}],"generic":"","nullable":false,"union":false,"idlType":"CSSOMString"},"extAttrs":[],"special":"","readonly":false},{"type":"attribute","name":"descentOverride","idlType":{"type":"attribute-type","extAttrs":[{"type":"extended-attribute","name":"LegacyNullToEmptyString","rhs":null,"arguments":[]}],"generic":"","nullable":false,"union":false,"idlType":"CSSOMString"},"extAttrs":[],"special":"","readonly":false},{"type":"attribute","name":"descent-override","idlType":{"type":"attribute-type","extAttrs":[{"type":"extended-attribute","name":"LegacyNullToEmptyString","rhs":null,"arguments":[]}],"generic":"","nullable":false,"union":false,"idlType":"CSSOMString"},"extAttrs":[],"special":"","readonly":false},{"type":"attribute","name":"lineGapOverride","idlType":{"type":"attribute-type","extAttrs":[{"type":"extended-attribute","name":"LegacyNullToEmptyString","rhs":null,"arguments":[]}],"generic":"","nullable":false,"union":false,"idlType":"CSSOMString"},"extAttrs":[],"special":"","readonly":false},{"type":"attribute","name":"line-gap-override","idlType":{"type":"attribute-type","extAttrs":[{"type":"extended-attribute","name":"LegacyNullToEmptyString","rhs":null,"arguments":[]}],"generic":"","nullable":false,"union":false,"idlType":"CSSOMString"},"extAttrs":[],"special":"","readonly":false},{"type":"attribute","name":"superscriptPositionOverride","idlType":{"type":"attribute-type","extAttrs":[{"type":"extended-attribute","name":"LegacyNullToEmptyString","rhs":null,"arguments":[]}],"generic":"","nullable":false,"union":false,"idlType":"CSSOMString"},"extAttrs":[],"special":"","readonly":false},{"type":"attribute","name":"superscript-position-override","idlType":{"type":"attribute-type","extAttrs":[{"type":"extended-attribute","name":"LegacyNullToEmptyString","rhs":null,"arguments":[]}],"generic":"","nullable":false,"union":false,"idlType":"CSSOMString"},"extAttrs":[],"special":"","readonly":false},{"type":"attribute","name":"subscriptPositionOverride","idlType":{"type":"attribute-type","extAttrs":[{"type":"extended-attribute","name":"LegacyNullToEmptyString","rhs":null,"arguments":[]}],"generic":"","nullable":false,"union":false,"idlType":"CSSOMString"},"extAttrs":[],"special":"","readonly":false},{"type":"attribute","name":"subscript-position-override","idlType":{"type":"attribute-type","extAttrs":[{"type":"extended-attribute","name":"LegacyNullToEmptyString","rhs":null,"arguments":[]}],"generic":"","nullable":false,"union":false,"idlType":"CSSOMString"},"extAttrs":[],"special":"","readonly":false},{"type":"attribute","name":"superscriptSizeOverride","idlType":{"type":"attribute-type","extAttrs":[{"type":"extended-attribute","name":"LegacyNullToEmptyString","rhs":null,"arguments":[]}],"generic":"","nullable":false,"union":false,"idlType":"CSSOMString"},"extAttrs":[],"special":"","readonly":false},{"type":"attribute","name":"superscript-size-override","idlType":{"type":"attribute-type","extAttrs":[{"type":"extended-attribute","name":"LegacyNullToEmptyString","rhs":null,"arguments":[]}],"generic":"","nullable":false,"union":false,"idlType":"CSSOMString"},"extAttrs":[],"special":"","readonly":false},{"type":"attribute","name":"subscriptSizeOverride","idlType":{"type":"attribute-type","extAttrs":[{"type":"extended-attribute","name":"LegacyNullToEmptyString","rhs":null,"arguments":[]}],"generic":"","nullable":false,"union":false,"idlType":"CSSOMString"},"extAttrs":[],"special":"","readonly":false},{"type":"attribute","name":"subscript-size-override","idlType":{"type":"attribute-type","extAttrs":[{"type":"extended-attribute","name":"LegacyNullToEmptyString","rhs":null,"arguments":[]}],"generic":"","nullable":false,"union":false,"idlType":"CSSOMString"},"extAttrs":[],"special":"","readonly":false}],"extAttrs":[{"type":"extended-attribute","name":"Exposed","rhs":{"type":"identifier","value":"Window"},"arguments":[]}],"partial":false},"CSSFontFaceRule":{"type":"interface","name":"CSSFontFaceRule","inheritance":"CSSRule","members":[{"type":"attribute","name":"style","idlType":{"type":"attribute-type","extAttrs":[],"generic":"","nullable":false,"union":false,"idlType":"CSSFontFaceDescriptors"},"extAttrs":[{"type":"extended-attribute","name":"SameObject","rhs":null,"arguments":[]},{"type":"extended-attribute","name":"PutForwards","rhs":{"type":"identifier","value":"cssText"},"arguments":[]}],"special":"","readonly":true}],"extAttrs":[{"type":"extended-attribute","name":"Exposed","rhs":{"type":"identifier","value":"Window"},"arguments":[]}],"partial":false}},"idlExtendedNames":{},"globals":{},"exposed":{"Window":["CSSFontFaceDescriptors","CSSFontFaceRule"]},"dependencies":{"CSSFontFaceDescriptors":["CSSStyleDeclaration","CSSOMString"],"CSSFontFaceRule":["CSSRule","CSSFontFaceDescriptors"]},"externalDependencies":["CSSStyleDeclaration","CSSOMString","CSSRule"],"hasObsoleteIdl":false}}
