{"spec":{"title":"CSSOM View Module","url":"https://drafts.csswg.org/cssom-view-1/"},"events":[{"src":{"format":"summary table"},"type":"change","targets":["MediaQueryList"],"interface":"MediaQueryListEvent"},{"src":{"format":"summary table"},"type":"resize","targets":["Window","VisualViewport"],"interface":"Event"},{"src":{"format":"summary table"},"type":"scroll","targets":["Document","Element","VisualViewport"],"interface":"Event","bubbles":true},{"src":{"format":"summary table"},"type":"scrollend","targets":["Document","Element","VisualViewport"],"interface":"Event","bubbles":true}]}
